odoo10_addon_website_sale_charge_payment_fee-10.0.1.0.2-nspkg.pth
odoo/addons/website_sale_charge_payment_fee/README.rst
odoo/addons/website_sale_charge_payment_fee/__init__.py
odoo/addons/website_sale_charge_payment_fee/__manifest__.py
odoo/addons/website_sale_charge_payment_fee/controllers/__init__.py
odoo/addons/website_sale_charge_payment_fee/controllers/website_sale.py
odoo/addons/website_sale_charge_payment_fee/i18n/it.po
odoo/addons/website_sale_charge_payment_fee/i18n/website_sale_charge_payment_fee.pot
odoo/addons/website_sale_charge_payment_fee/models/__init__.py
odoo/addons/website_sale_charge_payment_fee/models/payment.py
odoo/addons/website_sale_charge_payment_fee/models/sale.py
odoo/addons/website_sale_charge_payment_fee/readme/CONFIGURE.rst
odoo/addons/website_sale_charge_payment_fee/readme/CONTRIBUTORS.rst
odoo/addons/website_sale_charge_payment_fee/readme/DESCRIPTION.rst
odoo/addons/website_sale_charge_payment_fee/static/description/icon.png
odoo/addons/website_sale_charge_payment_fee/static/description/index.html
odoo/addons/website_sale_charge_payment_fee/static/src/js/website_sale_fee.js
odoo/addons/website_sale_charge_payment_fee/templates/website_sale.xml
odoo/addons/website_sale_charge_payment_fee/views/payment_view.xml
odoo10_addon_website_sale_charge_payment_fee-10.0.1.0.2.dist-info/METADATA
odoo10_addon_website_sale_charge_payment_fee-10.0.1.0.2.dist-info/WHEEL
odoo10_addon_website_sale_charge_payment_fee-10.0.1.0.2.dist-info/namespace_packages.txt
odoo10_addon_website_sale_charge_payment_fee-10.0.1.0.2.dist-info/top_level.txt
odoo10_addon_website_sale_charge_payment_fee-10.0.1.0.2.dist-info/RECORD
