Metadata-Version: 2.1
Name: odoo10-addon-website-sale-charge-payment-fee
Version: 10.0.1.0.2
Summary: Payment fee charged to customer
Home-page: https://github.com/OCA/e-commerce
Author: Agile Business Group, Odoo Community Association (OCA)
Author-email: support@odoo-community.org
License: LGPL-3
Platform: UNKNOWN
Classifier: Programming Language :: Python
Classifier: Framework :: Odoo
Classifier: License :: OSI Approved :: GNU Lesser General Public License v3 (LGPLv3)
Classifier: Development Status :: 4 - Beta
Requires-Python: ~=2.7
Requires-Dist: odoo (<10.1dev,>=10.0)
